zynk/__init__.py
zynk/bridge.py
zynk/channel.py
zynk/errors.py
zynk/generator.py
zynk/registry.py
zynk/runner.py
zynk/server.py
zynk-0.1.0.dist-info/licenses/LICENSE
zynk-0.1.0.dist-info/METADATA
zynk-0.1.0.dist-info/WHEEL
zynk-0.1.0.dist-info/entry_points.txt
zynk-0.1.0.dist-info/top_level.txt
zynk-0.1.0.dist-info/RECORD
