Metadata-Version: 2.4
Name: zynk
Version: 0.1.0
Summary: Bridge Python backends to TypeScript frontends with automatic type-safe client generation
Author: Zynk Team
License: MIT
Project-URL: Homepage, https://github.com/zynk/zynk
Project-URL: Documentation, https://github.com/zynk/zynk#readme
Project-URL: Repository, https://github.com/zynk/zynk
Keywords: typescript,fastapi,code-generation,type-safety,bridge,frontend,backend
Classifier: Development Status :: 4 - Beta
Classifier: Intended Audience :: Developers
Classifier: License :: OSI Approved :: MIT License
Classifier: Operating System :: OS Independent
Classifier: Programming Language :: Python :: 3
Classifier: Programming Language :: Python :: 3.10
Classifier: Programming Language :: Python :: 3.11
Classifier: Programming Language :: Python :: 3.12
Classifier: Framework :: FastAPI
Classifier: Topic :: Software Development :: Code Generators
Classifier: Topic :: Internet :: WWW/HTTP :: HTTP Servers
Classifier: Typing :: Typed
Requires-Python: >=3.10
License-File: LICENSE
Requires-Dist: fastapi>=0.100.0
Requires-Dist: uvicorn[standard]>=0.23.0
Requires-Dist: pydantic>=2.0.0
Requires-Dist: rich>=14.2.0
Requires-Dist: pytest>=9.0.2
Provides-Extra: dev
Requires-Dist: pytest>=7.0.0; extra == "dev"
Requires-Dist: pytest-asyncio>=0.21.0; extra == "dev"
Requires-Dist: httpx>=0.24.0; extra == "dev"
Requires-Dist: black>=23.0.0; extra == "dev"
Requires-Dist: ruff>=0.0.280; extra == "dev"
Requires-Dist: mypy>=1.4.0; extra == "dev"
Dynamic: license-file
